funkycam/__init__.py
funkycam/funkycam.py
funkycam-0.0.6.dist-info/LICENSE
funkycam-0.0.6.dist-info/METADATA
funkycam-0.0.6.dist-info/WHEEL
funkycam-0.0.6.dist-info/top_level.txt
funkycam-0.0.6.dist-info/RECORD
