Metadata-Version: 2.1
Name: funkycam
Version: 0.0.6
Summary: A small package to make funky video, images, and real-time video
Author: Luke Tambakis
Project-URL: Homepage, https://github.com/LTambam/funkycam
Classifier: Programming Language :: Python :: 3
Classifier: License :: OSI Approved :: MIT License
Classifier: Operating System :: OS Independent
Requires-Python: >=3.7
License-File: LICENSE
Requires-Dist: numpy
Requires-Dist: opencv-python
Requires-Dist: seaborn
